_cppstd.cp35-win32.pyd
cppstd/__init__.py
cppstd/hints.py
cppstd/map.py
cppstd/set.py
cppstd/vector.py
cppstd/core/__init__.py
cppstd/core/abcs.py
cppstd/core/hints.py
cppstd/core/red_black.py
cppstd/core/tokenization.py
cppstd/core/utils.py
cppstd-1.0.0.dist-info/LICENSE
cppstd-1.0.0.dist-info/METADATA
cppstd-1.0.0.dist-info/WHEEL
cppstd-1.0.0.dist-info/top_level.txt
cppstd-1.0.0.dist-info/RECORD
