Metadata-Version: 2.1
Name: cppstd
Version: 1.0.0
Summary: Partial port of C++ standard library.
Home-page: https://github.com/lycantropos/cppstd/
Author: Azat Ibrakov
Author-email: azatibrakov@gmail.com
License: MIT License
Download-URL: https://github.com/lycantropos/cppstd/archive/master.zip
Platform: UNKNOWN
Classifier: License :: OSI Approved :: MIT License
Classifier: Programming Language :: Python :: 3.5
Classifier: Programming Language :: Python :: 3.6
Classifier: Programming Language :: Python :: 3.7
Classifier: Programming Language :: Python :: 3.8
Classifier: Programming Language :: Python :: Implementation :: CPython
Requires-Python: >=3.5
Requires-Dist: reprit (>=0.3.0)
Requires-Dist: typing-extensions (>=3.7.4.2) ; python_version < "3.8"
